jumper_extension/__init__.py
jumper_extension/analyzer.py
jumper_extension/cell_history.py
jumper_extension/data.py
jumper_extension/extension_messages.py
jumper_extension/logging_config.py
jumper_extension/logo.py
jumper_extension/magics.py
jumper_extension/monitor.py
jumper_extension/reporter.py
jumper_extension/utilities.py
jumper_extension/visualizer.py
jumper_extension/templates/__init__.py
jumper_extension/templates/report/__init__.py
jumper_extension/templates/report/report.html
jumper_extension/templates/report/styles.css
jumper_extension-0.3.5.dist-info/licenses/LICENSE
jumper_extension-0.3.5.dist-info/METADATA
jumper_extension-0.3.5.dist-info/WHEEL
jumper_extension-0.3.5.dist-info/entry_points.txt
jumper_extension-0.3.5.dist-info/top_level.txt
jumper_extension-0.3.5.dist-info/RECORD
