Metadata-Version: 2.4
Name: jumper-extension
Version: 0.3.5
Summary: IPython extension for monitoring cell performance
Project-URL: Homepage, https://github.com/ScaDS/jumper_ipython_extension
Requires-Python: >=3.8
License-File: LICENSE
Requires-Dist: ipython
Requires-Dist: matplotlib
Requires-Dist: pandas
Requires-Dist: numpy
Requires-Dist: ipympl
Requires-Dist: psutil
Requires-Dist: itables
Requires-Dist: ipywidgets
Requires-Dist: jinja2
Provides-Extra: test
Requires-Dist: pytest; extra == "test"
Requires-Dist: pytest-mock; extra == "test"
Requires-Dist: pytest-cov; extra == "test"
Requires-Dist: pynvml; extra == "test"
Dynamic: license-file
